LICENSE
MANIFEST.in
README.md
pyproject.toml
setup.cfg
setup.py
django_event_cal/__init__.py
django_event_cal/admin.py
django_event_cal/apps.py
django_event_cal/forms.py
django_event_cal/functions.py
django_event_cal/models.py
django_event_cal/tests.py
django_event_cal/urls.py
django_event_cal/views.py
django_event_cal.egg-info/PKG-INFO
django_event_cal.egg-info/SOURCES.txt
django_event_cal.egg-info/dependency_links.txt
django_event_cal.egg-info/requires.txt
django_event_cal.egg-info/top_level.txt
django_event_cal/migrations/__init__.py
django_event_cal/templates/events_cal/base.html
django_event_cal/templates/events_cal/event.html